allescacher/README.MD
allescacher/__init__.py
allescacher/requirements.txt
allescacher/thirdparty.json
allescacher-0.10.dist-info/LICENSE.rst
allescacher-0.10.dist-info/METADATA
allescacher-0.10.dist-info/WHEEL
allescacher-0.10.dist-info/top_level.txt
allescacher-0.10.dist-info/RECORD
