Metadata-Version: 2.1
Name: allescacher
Version: 0.10
Summary: Like @functools.cache / @functools.lru_cache but with non-hashable objects
Home-page: https://github.com/hansalemaos/allescacher
Author: Johannes Fischer
Author-email: aulasparticularesdealemaosp@gmail.com
License: MIT
Keywords: cache,@functools.lru_cache,@functools.cache
Classifier: Development Status :: 4 - Beta
Classifier: Programming Language :: Python :: 3 :: Only
Classifier: Programming Language :: Python :: 3.10
Classifier: Topic :: Software Development :: Libraries :: Python Modules
Classifier: Topic :: Utilities
License-File: LICENSE.rst
